pyaraucaria/__init__.py
pyaraucaria/airmass.py
pyaraucaria/coordinates.py
pyaraucaria/date.py
pyaraucaria/dome_eq.py
pyaraucaria/ephemeris.py
pyaraucaria/erfa.py
pyaraucaria/ffs.py
pyaraucaria/find_stars.py
pyaraucaria/fits.py
pyaraucaria/focus.py
pyaraucaria/libobject.py
pyaraucaria/lookup_objects.py
pyaraucaria/reddening.py
pyaraucaria/databases/Objects.database
pyaraucaria/databases/TAB.ALL
pyaraucaria/databases/lmc_res5_radius5.txt
pyaraucaria/obs_plan/obs_plan_parser.py
pyaraucaria/obs_plan/obsplan.md
pyaraucaria-2.11.2.dist-info/METADATA
pyaraucaria-2.11.2.dist-info/WHEEL
pyaraucaria-2.11.2.dist-info/entry_points.txt
pyaraucaria-2.11.2.dist-info/licenses/LICENSE
pyaraucaria-2.11.2.dist-info/RECORD
