Metadata-Version: 2.4
Name: pyaraucaria
Version: 2.11.2
Summary: Common Routines of OCA Observatory and Araucaria Project
Project-URL: Homepage, https://github.com/araucaria-project/pyaraucaria
Project-URL: Repository, https://github.com/araucaria-project/pyaraucaria
Author: Araucaria Project
License-Expression: LGPL-3.0-or-later
License-File: LICENSE
Classifier: Development Status :: 4 - Beta
Classifier: Intended Audience :: Science/Research
Classifier: License :: OSI Approved :: GNU Lesser General Public License v3 or later (LGPLv3+)
Classifier: Programming Language :: Python :: 3
Classifier: Programming Language :: Python :: 3.10
Classifier: Programming Language :: Python :: 3.11
Classifier: Programming Language :: Python :: 3.12
Classifier: Programming Language :: Python :: 3.13
Classifier: Topic :: Scientific/Engineering :: Astronomy
Requires-Python: >=3.10
Requires-Dist: astroplan
Requires-Dist: astropy
Requires-Dist: ephem
Requires-Dist: lark
Requires-Dist: matplotlib
Requires-Dist: numpy
Requires-Dist: scipy
Provides-Extra: dev
Provides-Extra: yaml
Requires-Dist: pyyaml; extra == 'yaml'
